Metadata-Version: 2.2
Name: dpysts
Version: 0.0.1
Summary: STS python client
Home-page: https://github.com/your_username/your_package
Author: YUJING
Author-email: yujing@dianxiaomi.com
Classifier: Programming Language :: Python :: 3
Classifier: License :: OSI Approved :: MIT License
Classifier: Operating System :: OS Independent
Requires-Python: >=3.8
License-File: LICENSE
Requires-Dist: requests>=2.28.2
Dynamic: author
Dynamic: author-email
Dynamic: classifier
Dynamic: description
Dynamic: description-content-type
Dynamic: home-page
Dynamic: requires-python
Dynamic: summary
